{
  "padrones": [
    {
      "PedidoCoberturaPadronId": 181513,
      "Prioridad": null,
      "Convocatoria": "CONCENTRACION 2023",
      "Organizacion": "ESCUELA SUPERIOR DE EDUCACION ARTISTICA (E.S.E.A.)                                                                                                                                                                                                        ",
      "Nivel": "",
      "Cargo": "HORAS CATEDRAS SECUNDARIAS - 801",
      "Asignatura": "FORMACION ETICA/ FORMACION RELIGIOSA",
      "Especialidad": "",
      "ConCargo": "",
      "Url": "https://drive.google.com/file/d/1ix4T8_K3JZkbcvh3Lu61CoBDlXkNYwsI/view"
    },
    {
      "PedidoCoberturaPadronId": 181516,
      "Prioridad": null,
      "Convocatoria": "INTERINATOS Y SUPLENCIAS 2023",
      "Organizacion": "CIRCUITO II (CAPITAL)                                                                                                                                                                                                                                     ",
      "Nivel": "",
      "Cargo": "HORAS CATEDRAS SECUNDARIAS - 801",
      "Asignatura": "FORMACION ETICA/ FORMACION RELIGIOSA",
      "Especialidad": "",
      "ConCargo": "",
      "Url": "https://drive.google.com/file/d/1swil7kE8zOeyd5UzIH7XTe38__TmaKnO/view"
    },
    {
      "PedidoCoberturaPadronId": 181518,
      "Prioridad": null,
      "Convocatoria": "INTERINATOS Y SUPLENCIAS 2023",
      "Organizacion": "CIRCUITO II (CAPITAL)                                                                                                                                                                                                                                     ",
      "Nivel": "",
      "Cargo": "HORAS CATEDRAS SECUNDARIAS - 801",
      "Asignatura": "FORMACION MORAL/RELIGION",
      "Especialidad": "",
      "ConCargo": "",
      "Url": "https://drive.google.com/file/d/1swil7kE8zOeyd5UzIH7XTe38__TmaKnO/view"
    },
    {
      "PedidoCoberturaPadronId": 181519,
      "Prioridad": null,
      "Convocatoria": "CONCENTRACION 2023",
      "Organizacion": "ESCUELA SUPERIOR DE EDUCACION ARTISTICA (E.S.E.A.)                                                                                                                                                                                                        ",
      "Nivel": "",
      "Cargo": "HORAS CATEDRAS SECUNDARIAS - 801",
      "Asignatura": "FORMACION ETICA Y CIUDADANA",
      "Especialidad": "",
      "ConCargo": "",
      "Url": "https://drive.google.com/file/d/1ix4T8_K3JZkbcvh3Lu61CoBDlXkNYwsI/view"
    },
    {
      "PedidoCoberturaPadronId": 181524,
      "Prioridad": null,
      "Convocatoria": "INTERINATOS Y SUPLENCIAS 2023",
      "Organizacion": "CIRCUITO II (CAPITAL)                                                                                                                                                                                                                                     ",
      "Nivel": "",
      "Cargo": "HORAS CATEDRAS SECUNDARIAS - 801",
      "Asignatura": "FORMACION ETICA Y CIUDADANA",
      "Especialidad": "",
      "ConCargo": "",
      "Url": "https://drive.google.com/file/d/1swil7kE8zOeyd5UzIH7XTe38__TmaKnO/view"
    },
    {
      "PedidoCoberturaPadronId": 181528,
      "Prioridad": null,
      "Convocatoria": "CONCENTRACION 2023",
      "Organizacion": "ESCUELA SUPERIOR DE EDUCACION ARTISTICA (E.S.E.A.)                                                                                                                                                                                                        ",
      "Nivel": "",
      "Cargo": "HORAS CATEDRAS SECUNDARIAS - 801",
      "Asignatura": "FILOSOFIA",
      "Especialidad": "",
      "ConCargo": "",
      "Url": "https://drive.google.com/file/d/1ix4T8_K3JZkbcvh3Lu61CoBDlXkNYwsI/view"
    },
    {
      "PedidoCoberturaPadronId": 181544,
      "Prioridad": null,
      "Convocatoria": "INTERINATOS Y SUPLENCIAS 2023",
      "Organizacion": "CIRCUITO II (CAPITAL)                                                                                                                                                                                                                                     ",
      "Nivel": "",
      "Cargo": "HORAS CATEDRAS SECUNDARIAS - 801",
      "Asignatura": "FILOSOFIA",
      "Especialidad": "",
      "ConCargo": "",
      "Url": "https://drive.google.com/file/d/1swil7kE8zOeyd5UzIH7XTe38__TmaKnO/view"
    },
    {
      "PedidoCoberturaPadronId": 181548,
      "Prioridad": null,
      "Convocatoria": "INTERINATOS Y SUPLENCIAS 2023",
      "Organizacion": "CIRCUITO II (CAPITAL)                                                                                                                                                                                                                                     ",
      "Nivel": "",
      "Cargo": "HORAS CATEDRAS SECUNDARIAS - 801",
      "Asignatura": "SOCIOLOGIA",
      "Especialidad": "",
      "ConCargo": "",
      "Url": "https://drive.google.com/file/d/1swil7kE8zOeyd5UzIH7XTe38__TmaKnO/view"
    },
    {
      "PedidoCoberturaPadronId": 181551,
      "Prioridad": null,
      "Convocatoria": "CONCENTRACION 2023",
      "Organizacion": "ESCUELA SUPERIOR DE EDUCACION ARTISTICA (E.S.E.A.)                                                                                                                                                                                                        ",
      "Nivel": "",
      "Cargo": "HORAS CATEDRAS SECUNDARIAS - 801",
      "Asignatura": "HISTORIA",
      "Especialidad": "",
      "ConCargo": "",
      "Url": "https://drive.google.com/file/d/1ix4T8_K3JZkbcvh3Lu61CoBDlXkNYwsI/view"
    },
    {
      "PedidoCoberturaPadronId": 181555,
      "Prioridad": null,
      "Convocatoria": "INTERINATOS Y SUPLENCIAS 2023",
      "Organizacion": "CIRCUITO II (CAPITAL)                                                                                                                                                                                                                                     ",
      "Nivel": "",
      "Cargo": "HORAS CATEDRAS SECUNDARIAS - 801",
      "Asignatura": "HISTORIA",
      "Especialidad": "",
      "ConCargo": "",
      "Url": "https://drive.google.com/file/d/1swil7kE8zOeyd5UzIH7XTe38__TmaKnO/view"
    }
  ]
}
