{
  "metadata": {
    "vacante_id": 63564,
    "padron_id": 113161
  },
  "postulantes": [
    {
      "orden": 38,
      "dni": "29XXXX89",
      "apellidos": "SAEZ GARCÍA",
      "nombres": "MARÍA DEL CARMEN",
      "TipoCircuito": "CIRC. CON RESIDENCIA",
      "CategoriaTitulo": "DOCENTE",
      "CargoInferior": "-"
    },
    {
      "orden": 67,
      "dni": "29XXXX62",
      "apellidos": "SCARAVILLI",
      "nombres": "ROMINA MARIA",
      "TipoCircuito": "CIRC. CON RESIDENCIA",
      "CategoriaTitulo": "DOCENTE",
      "CargoInferior": "-"
    },
    {
      "orden": 82,
      "dni": "27XXXX81",
      "apellidos": "MORENO LAGORIA",
      "nombres": "ROXANA ANGELICA",
      "TipoCircuito": "CIRC. CON RESIDENCIA",
      "CategoriaTitulo": "DOCENTE",
      "CargoInferior": "-"
    },
    {
      "orden": 88,
      "dni": "32XXXX49",
      "apellidos": "BAUTISTA FLORES",
      "nombres": "RUTH ELENA",
      "TipoCircuito": "CIRC. CON RESIDENCIA",
      "CategoriaTitulo": "DOCENTE",
      "CargoInferior": "-"
    },
    {
      "orden": 184,
      "dni": "34XXXX18",
      "apellidos": "LECHESI",
      "nombres": "LAURA VICTORIA",
      "TipoCircuito": "CIRC. CON RESIDENCIA",
      "CategoriaTitulo": "DOCENTE",
      "CargoInferior": "-"
    },
    {
      "orden": 238,
      "dni": "32XXXX30",
      "apellidos": "DANNA",
      "nombres": "YESICA DANIELA",
      "TipoCircuito": "CIRC. CON RESIDENCIA",
      "CategoriaTitulo": "DOCENTE",
      "CargoInferior": "-"
    },
    {
      "orden": 244,
      "dni": "20XXXX59",
      "apellidos": "AMUN",
      "nombres": "FATIMA ALEJANDRA",
      "TipoCircuito": "CIRC. CON RESIDENCIA",
      "CategoriaTitulo": "DOCENTE",
      "CargoInferior": "-"
    },
    {
      "orden": 285,
      "dni": "40XXXX12",
      "apellidos": "CANTO",
      "nombres": "FLAVIA SABRINA",
      "TipoCircuito": "CIRC. CON RESIDENCIA",
      "CategoriaTitulo": "DOCENTE",
      "CargoInferior": "-"
    },
    {
      "orden": 302,
      "dni": "38XXXX73",
      "apellidos": "BUSTOS",
      "nombres": "MARIA DEL PILAR",
      "TipoCircuito": "CIRC. CON RESIDENCIA",
      "CategoriaTitulo": "DOCENTE",
      "CargoInferior": "-"
    },
    {
      "orden": 331,
      "dni": "26XXXX91",
      "apellidos": "SEQUEIRA",
      "nombres": "NANCY MARIELA",
      "TipoCircuito": "CIRC. CON RESIDENCIA",
      "CategoriaTitulo": "DOCENTE",
      "CargoInferior": "-"
    },
    {
      "orden": 11,
      "dni": "25XXXX73",
      "apellidos": "HERRERA",
      "nombres": "MARIA ISABEL",
      "TipoCircuito": "CIRC. CON RESIDENCIA",
      "CategoriaTitulo": "SUPLETORIO",
      "CargoInferior": "-"
    },
    {
      "orden": 60,
      "dni": "34XXXX19",
      "apellidos": "DEL VALLE",
      "nombres": "GISELA CELESTE",
      "TipoCircuito": "CIRC. SIN RESIDENCIA",
      "CategoriaTitulo": "DOCENTE",
      "CargoInferior": "-"
    },
    {
      "orden": 70,
      "dni": "38XXXX58",
      "apellidos": "BULACIO",
      "nombres": "LUCIANA AGUSTINA",
      "TipoCircuito": "CIRC. SIN RESIDENCIA",
      "CategoriaTitulo": "DOCENTE",
      "CargoInferior": "-"
    }
  ]
}
