{
  "metadata": {
    "vacante_id": 45789,
    "padron_id": 81623
  },
  "postulantes": [
    {
      "orden": null,
      "dni": "32XXXX66",
      "apellidos": "ARIAS LEROUX",
      "nombres": "ROSSANA DEL VALLE",
      "TipoCircuito": "-",
      "CategoriaTitulo": "-",
      "CargoInferior": "-"
    },
    {
      "orden": null,
      "dni": "17XXXX58",
      "apellidos": "DARNAY",
      "nombres": "ROBERTO EDUARDO",
      "TipoCircuito": "-",
      "CategoriaTitulo": "-",
      "CargoInferior": "-"
    },
    {
      "orden": null,
      "dni": "22XXXX73",
      "apellidos": "DECIMA",
      "nombres": "ANGEL CLAUDIO DARIO",
      "TipoCircuito": "-",
      "CategoriaTitulo": "-",
      "CargoInferior": "-"
    },
    {
      "orden": null,
      "dni": "31XXXX23",
      "apellidos": "FLORES AHUMADA",
      "nombres": "MARIANO LUIS GERONIMO",
      "TipoCircuito": "-",
      "CategoriaTitulo": "-",
      "CargoInferior": "-"
    },
    {
      "orden": null,
      "dni": "33XXXX40",
      "apellidos": "MARTINEZ",
      "nombres": "REGINA NELLY",
      "TipoCircuito": "-",
      "CategoriaTitulo": "-",
      "CargoInferior": "-"
    },
    {
      "orden": null,
      "dni": "21XXXX82",
      "apellidos": "PALINA",
      "nombres": "JUAN RAMON",
      "TipoCircuito": "-",
      "CategoriaTitulo": "-",
      "CargoInferior": "-"
    },
    {
      "orden": null,
      "dni": "26XXXX41",
      "apellidos": "TOLOSA",
      "nombres": "DIEGO",
      "TipoCircuito": "-",
      "CategoriaTitulo": "-",
      "CargoInferior": "-"
    },
    {
      "orden": null,
      "dni": "28XXXX56",
      "apellidos": "VITAR",
      "nombres": "GEORGINA LEONOR",
      "TipoCircuito": "-",
      "CategoriaTitulo": "-",
      "CargoInferior": "-"
    }
  ]
}
