{
  "metadata": {
    "vacante_id": 66970,
    "padron_id": 119320
  },
  "postulantes": [
    {
      "orden": 1,
      "dni": "25XXXX97",
      "apellidos": "DELGADO",
      "nombres": "MARIA JULIETA",
      "TipoCircuito": "NINGUNO",
      "CategoriaTitulo": "DOCENTE - INCUMBENCIA CURRICULAR",
      "CargoInferior": "-"
    },
    {
      "orden": 8,
      "dni": "34XXXX19",
      "apellidos": "MIRANDA GOMEZ",
      "nombres": "MARIA CONSTANZA",
      "TipoCircuito": "NINGUNO",
      "CategoriaTitulo": "DOCENTE - INCUMBENCIA CURRICULAR",
      "CargoInferior": "-"
    },
    {
      "orden": 17,
      "dni": "31XXXX86",
      "apellidos": "ZURITA",
      "nombres": "MARTA ROXANA",
      "TipoCircuito": "NINGUNO",
      "CategoriaTitulo": "DOCENTE - INCUMBENCIA CURRICULAR",
      "CargoInferior": "-"
    },
    {
      "orden": 21,
      "dni": "31XXXX71",
      "apellidos": "LEONE",
      "nombres": "DANIELA PAOLA",
      "TipoCircuito": "NINGUNO",
      "CategoriaTitulo": "DOCENTE - INCUMBENCIA CURRICULAR",
      "CargoInferior": "-"
    }
  ]
}
