{
  "metadata": {
    "vacante_id": 70248,
    "padron_id": 124868
  },
  "postulantes": [
    {
      "orden": 3,
      "dni": "30XXXX28",
      "apellidos": "BULACIO",
      "nombres": "MONICA ALEJANDRA",
      "TipoCircuito": "NINGUNO",
      "CategoriaTitulo": "DOCENTE",
      "CargoInferior": "-"
    },
    {
      "orden": 16,
      "dni": "29XXXX46",
      "apellidos": "JUAREZ",
      "nombres": "MARIA CRISTINA",
      "TipoCircuito": "NINGUNO",
      "CategoriaTitulo": "DOCENTE",
      "CargoInferior": "-"
    },
    {
      "orden": 31,
      "dni": "32XXXX11",
      "apellidos": "DIAZ MANZUR",
      "nombres": "MARIA VERONICA",
      "TipoCircuito": "NINGUNO",
      "CategoriaTitulo": "DOCENTE",
      "CargoInferior": "-"
    },
    {
      "orden": 36,
      "dni": "34XXXX40",
      "apellidos": "MORENO LUJAN",
      "nombres": "CONSTANZA JANET",
      "TipoCircuito": "NINGUNO",
      "CategoriaTitulo": "DOCENTE",
      "CargoInferior": "-"
    },
    {
      "orden": 37,
      "dni": "26XXXX29",
      "apellidos": "MAGARZO",
      "nombres": "JUAN RODOLFO",
      "TipoCircuito": "NINGUNO",
      "CategoriaTitulo": "DOCENTE",
      "CargoInferior": "-"
    },
    {
      "orden": 38,
      "dni": "35XXXX01",
      "apellidos": "BANDA",
      "nombres": "BRENDA SABRINA",
      "TipoCircuito": "NINGUNO",
      "CategoriaTitulo": "DOCENTE",
      "CargoInferior": "-"
    },
    {
      "orden": 44,
      "dni": "35XXXX35",
      "apellidos": "ZELARAYAN",
      "nombres": "JULIA ISABEL",
      "TipoCircuito": "NINGUNO",
      "CategoriaTitulo": "DOCENTE",
      "CargoInferior": "-"
    },
    {
      "orden": 48,
      "dni": "37XXXX02",
      "apellidos": "MEDINA",
      "nombres": "MACARENA FATIMA DEL VALLE",
      "TipoCircuito": "NINGUNO",
      "CategoriaTitulo": "DOCENTE",
      "CargoInferior": "-"
    },
    {
      "orden": 49,
      "dni": "29XXXX96",
      "apellidos": "CAMPOS",
      "nombres": "PABLO DAVID",
      "TipoCircuito": "NINGUNO",
      "CategoriaTitulo": "DOCENTE",
      "CargoInferior": "-"
    },
    {
      "orden": 52,
      "dni": "38XXXX06",
      "apellidos": "BARRIONUEVO",
      "nombres": "MARINA DEL ROSARIO",
      "TipoCircuito": "NINGUNO",
      "CategoriaTitulo": "DOCENTE",
      "CargoInferior": "-"
    },
    {
      "orden": 56,
      "dni": "37XXXX94",
      "apellidos": "SALAZAR",
      "nombres": "PATRICIA DEL VALLE",
      "TipoCircuito": "NINGUNO",
      "CategoriaTitulo": "DOCENTE",
      "CargoInferior": "-"
    },
    {
      "orden": 63,
      "dni": "37XXXX03",
      "apellidos": "CHICO",
      "nombres": "LOURDES JACKELINE",
      "TipoCircuito": "NINGUNO",
      "CategoriaTitulo": "DOCENTE",
      "CargoInferior": "-"
    },
    {
      "orden": 66,
      "dni": "35XXXX62",
      "apellidos": "LESCANO",
      "nombres": "MARIA LEILA",
      "TipoCircuito": "NINGUNO",
      "CategoriaTitulo": "DOCENTE",
      "CargoInferior": "-"
    },
    {
      "orden": 68,
      "dni": "31XXXX26",
      "apellidos": "ROSTAGNO",
      "nombres": "ANTONIA CINTIA PAOLA",
      "TipoCircuito": "NINGUNO",
      "CategoriaTitulo": "DOCENTE",
      "CargoInferior": "-"
    },
    {
      "orden": 73,
      "dni": "40XXXX33",
      "apellidos": "PEREZ",
      "nombres": "CARLA NATALIA",
      "TipoCircuito": "NINGUNO",
      "CategoriaTitulo": "DOCENTE",
      "CargoInferior": "-"
    },
    {
      "orden": 84,
      "dni": "36XXXX57",
      "apellidos": "MASCARINI",
      "nombres": "STEFANIA ALEJANDRA",
      "TipoCircuito": "NINGUNO",
      "CategoriaTitulo": "DOCENTE",
      "CargoInferior": "-"
    },
    {
      "orden": 88,
      "dni": "36XXXX50",
      "apellidos": "RACEDO",
      "nombres": "MARIA ANTONELLA",
      "TipoCircuito": "NINGUNO",
      "CategoriaTitulo": "DOCENTE",
      "CargoInferior": "-"
    }
  ]
}
