{
  "metadata": {
    "vacante_id": 20910,
    "padron_id": 38590
  },
  "postulantes": [
    {
      "orden": 0,
      "dni": "23XXXX91",
      "apellidos": "ACOSTA LOPEZ",
      "nombres": "MARIA ALEJANDRA",
      "TipoCircuito": "-",
      "CategoriaTitulo": "-",
      "CargoInferior": "-"
    },
    {
      "orden": 0,
      "dni": "25XXXX69",
      "apellidos": "ANTON",
      "nombres": "MONICA CECILIA",
      "TipoCircuito": "-",
      "CategoriaTitulo": "-",
      "CargoInferior": "-"
    },
    {
      "orden": 0,
      "dni": "26XXXX07",
      "apellidos": "BALCARCE",
      "nombres": "VANESA ALEJANDRA",
      "TipoCircuito": "-",
      "CategoriaTitulo": "-",
      "CargoInferior": "-"
    },
    {
      "orden": 0,
      "dni": "27XXXX87",
      "apellidos": "BUSTOS MORON",
      "nombres": "MARIA ELENA",
      "TipoCircuito": "-",
      "CategoriaTitulo": "-",
      "CargoInferior": "-"
    },
    {
      "orden": 0,
      "dni": "29XXXX47",
      "apellidos": "CACERES LUCENA",
      "nombres": "CRISTIAN EXEQUIEL",
      "TipoCircuito": "-",
      "CategoriaTitulo": "-",
      "CargoInferior": "-"
    },
    {
      "orden": 0,
      "dni": "33XXXX10",
      "apellidos": "CUEVAS",
      "nombres": "KARINA MABEL",
      "TipoCircuito": "-",
      "CategoriaTitulo": "-",
      "CargoInferior": "-"
    },
    {
      "orden": 0,
      "dni": "29XXXX58",
      "apellidos": "DELGADINO",
      "nombres": "SILVANA SOLEDAD",
      "TipoCircuito": "-",
      "CategoriaTitulo": "-",
      "CargoInferior": "-"
    },
    {
      "orden": 0,
      "dni": "29XXXX95",
      "apellidos": "ESPASA PRETEL",
      "nombres": "MARIA SOLEDAD",
      "TipoCircuito": "-",
      "CategoriaTitulo": "-",
      "CargoInferior": "-"
    },
    {
      "orden": 0,
      "dni": "34XXXX66",
      "apellidos": "GONZALEZ",
      "nombres": "JUAN MARTIN",
      "TipoCircuito": "-",
      "CategoriaTitulo": "-",
      "CargoInferior": "-"
    },
    {
      "orden": 0,
      "dni": "16XXXX09",
      "apellidos": "HERRERA",
      "nombres": "ADELA FATIMA",
      "TipoCircuito": "-",
      "CategoriaTitulo": "-",
      "CargoInferior": "-"
    },
    {
      "orden": 0,
      "dni": "30XXXX53",
      "apellidos": "JUAREZ",
      "nombres": "SILVANA",
      "TipoCircuito": "-",
      "CategoriaTitulo": "-",
      "CargoInferior": "-"
    },
    {
      "orden": 0,
      "dni": "38XXXX02",
      "apellidos": "LARA",
      "nombres": "MARINO LUCAS",
      "TipoCircuito": "-",
      "CategoriaTitulo": "-",
      "CargoInferior": "-"
    },
    {
      "orden": 0,
      "dni": "31XXXX70",
      "apellidos": "LOPEZ PEÑA",
      "nombres": "JORGE RAMON",
      "TipoCircuito": "-",
      "CategoriaTitulo": "-",
      "CargoInferior": "-"
    },
    {
      "orden": 0,
      "dni": "30XXXX24",
      "apellidos": "LUNA",
      "nombres": "MARIA FERNANDA",
      "TipoCircuito": "-",
      "CategoriaTitulo": "-",
      "CargoInferior": "-"
    },
    {
      "orden": 0,
      "dni": "32XXXX05",
      "apellidos": "MENDIA                                  ",
      "nombres": "MARIA BELEN                             ",
      "TipoCircuito": "-",
      "CategoriaTitulo": "-",
      "CargoInferior": "-"
    },
    {
      "orden": 0,
      "dni": "32XXXX75",
      "apellidos": "MENENDEZ ROLDAN",
      "nombres": "MARIA LUZ",
      "TipoCircuito": "-",
      "CategoriaTitulo": "-",
      "CargoInferior": "-"
    },
    {
      "orden": 0,
      "dni": "32XXXX12",
      "apellidos": "NARANJO",
      "nombres": "CLAUDIA NATALI",
      "TipoCircuito": "-",
      "CategoriaTitulo": "-",
      "CargoInferior": "-"
    },
    {
      "orden": 0,
      "dni": "33XXXX78",
      "apellidos": "NAVARRO",
      "nombres": "IVANA VANESA",
      "TipoCircuito": "-",
      "CategoriaTitulo": "-",
      "CargoInferior": "-"
    },
    {
      "orden": 0,
      "dni": "30XXXX61",
      "apellidos": "PEDERNERA",
      "nombres": "ANA LUCIA",
      "TipoCircuito": "-",
      "CategoriaTitulo": "-",
      "CargoInferior": "-"
    },
    {
      "orden": 0,
      "dni": "36XXXX68",
      "apellidos": "QUESSA",
      "nombres": "FERNANDO DAVID",
      "TipoCircuito": "-",
      "CategoriaTitulo": "-",
      "CargoInferior": "-"
    },
    {
      "orden": 0,
      "dni": "28XXXX85",
      "apellidos": "ROBLES H ANASTASIADIS",
      "nombres": "SILVINA VANESSA",
      "TipoCircuito": "-",
      "CategoriaTitulo": "-",
      "CargoInferior": "-"
    },
    {
      "orden": 0,
      "dni": "33XXXX62",
      "apellidos": "SADER",
      "nombres": "ANA SOFIA",
      "TipoCircuito": "-",
      "CategoriaTitulo": "-",
      "CargoInferior": "-"
    },
    {
      "orden": 0,
      "dni": "21XXXX68",
      "apellidos": "SIVILA",
      "nombres": "CAROLINA LEONOR",
      "TipoCircuito": "-",
      "CategoriaTitulo": "-",
      "CargoInferior": "-"
    },
    {
      "orden": 0,
      "dni": "21XXXX65",
      "apellidos": "TEMOCHE ROMERO",
      "nombres": "EDDA",
      "TipoCircuito": "-",
      "CategoriaTitulo": "-",
      "CargoInferior": "-"
    },
    {
      "orden": 0,
      "dni": "27XXXX14",
      "apellidos": "TETU",
      "nombres": "ANA LIA",
      "TipoCircuito": "-",
      "CategoriaTitulo": "-",
      "CargoInferior": "-"
    },
    {
      "orden": 0,
      "dni": "36XXXX04",
      "apellidos": "VERA LOPEZ",
      "nombres": "FRANCO AUGUSTO",
      "TipoCircuito": "-",
      "CategoriaTitulo": "-",
      "CargoInferior": "-"
    }
  ]
}
