{
  "metadata": {
    "vacante_id": 53607,
    "padron_id": 95696
  },
  "postulantes": [
    {
      "orden": 41,
      "dni": "21XXXX10",
      "apellidos": "DIAZ",
      "nombres": "ADRIANA SUSANA",
      "TipoCircuito": "CON RESIDENCIA",
      "CategoriaTitulo": "DOCENTE",
      "CargoInferior": "-"
    },
    {
      "orden": 210,
      "dni": "22XXXX96",
      "apellidos": "JUAREZ",
      "nombres": "SILVIA CECILIA",
      "TipoCircuito": "CON RESIDENCIA",
      "CategoriaTitulo": "DOCENTE",
      "CargoInferior": "-"
    },
    {
      "orden": 450,
      "dni": "32XXXX24",
      "apellidos": "ZAIN",
      "nombres": "NATALIA ELIZABETH",
      "TipoCircuito": "CON RESIDENCIA",
      "CategoriaTitulo": "DOCENTE",
      "CargoInferior": "-"
    },
    {
      "orden": 495,
      "dni": "21XXXX94",
      "apellidos": "HERRERA",
      "nombres": "ANALIA LUISA DEL VALLE",
      "TipoCircuito": "CON RESIDENCIA",
      "CategoriaTitulo": "DOCENTE",
      "CargoInferior": "-"
    },
    {
      "orden": 498,
      "dni": "33XXXX02",
      "apellidos": "VERA",
      "nombres": "LUCIANA NOELIA",
      "TipoCircuito": "CON RESIDENCIA",
      "CategoriaTitulo": "DOCENTE",
      "CargoInferior": "-"
    },
    {
      "orden": 514,
      "dni": "32XXXX91",
      "apellidos": "ROMANO",
      "nombres": "CECILIA NATALI",
      "TipoCircuito": "CON RESIDENCIA",
      "CategoriaTitulo": "DOCENTE",
      "CargoInferior": "-"
    },
    {
      "orden": 522,
      "dni": "21XXXX44",
      "apellidos": "FUENTES",
      "nombres": "SILVIA ISABEL",
      "TipoCircuito": "CON RESIDENCIA",
      "CategoriaTitulo": "DOCENTE",
      "CargoInferior": "-"
    },
    {
      "orden": 567,
      "dni": "36XXXX64",
      "apellidos": "CORREA",
      "nombres": "PAOLA NATALIA",
      "TipoCircuito": "CON RESIDENCIA",
      "CategoriaTitulo": "DOCENTE",
      "CargoInferior": "-"
    },
    {
      "orden": 579,
      "dni": "36XXXX79",
      "apellidos": "ALE",
      "nombres": "MARIA BEATRIZ",
      "TipoCircuito": "CON RESIDENCIA",
      "CategoriaTitulo": "DOCENTE",
      "CargoInferior": "-"
    },
    {
      "orden": 721,
      "dni": "37XXXX56",
      "apellidos": "CORREA",
      "nombres": "JOHANA ELIZABETH",
      "TipoCircuito": "CON RESIDENCIA",
      "CategoriaTitulo": "DOCENTE",
      "CargoInferior": "-"
    },
    {
      "orden": 743,
      "dni": "36XXXX24",
      "apellidos": "FERRO",
      "nombres": "AUGUSTO EZEQUIEL",
      "TipoCircuito": "CON RESIDENCIA",
      "CategoriaTitulo": "DOCENTE",
      "CargoInferior": "-"
    },
    {
      "orden": 766,
      "dni": "33XXXX20",
      "apellidos": "PAZ",
      "nombres": "PAOLA GABRIELA",
      "TipoCircuito": "CON RESIDENCIA",
      "CategoriaTitulo": "DOCENTE",
      "CargoInferior": "-"
    },
    {
      "orden": 833,
      "dni": "22XXXX99",
      "apellidos": "FIAD",
      "nombres": "MARIA CECILIA",
      "TipoCircuito": "SIN RESIDENCIA",
      "CategoriaTitulo": "DOCENTE",
      "CargoInferior": "-"
    }
  ]
}
