{
  "metadata": {
    "vacante_id": 96924,
    "padron_id": 169480
  },
  "postulantes": [
    {
      "orden": 5,
      "dni": "34XXXX14",
      "apellidos": "MORÁN",
      "nombres": "CYNTHIA DANIELA",
      "TipoCircuito": "CIRC. CON RESIDENCIA",
      "CategoriaTitulo": "DOCENTE",
      "CargoInferior": "-"
    },
    {
      "orden": 9,
      "dni": "31XXXX19",
      "apellidos": "FIGUEROA CAMPOS",
      "nombres": "LUCIANA",
      "TipoCircuito": "CIRC. CON RESIDENCIA",
      "CategoriaTitulo": "DOCENTE",
      "CargoInferior": "-"
    },
    {
      "orden": 22,
      "dni": "20XXXX17",
      "apellidos": "SARDO",
      "nombres": "SARA MARTINA",
      "TipoCircuito": "CIRC. CON RESIDENCIA",
      "CategoriaTitulo": "DOCENTE",
      "CargoInferior": "-"
    },
    {
      "orden": 25,
      "dni": "26XXXX81",
      "apellidos": "GALLARDO",
      "nombres": "VIVIANA DEL VALLE",
      "TipoCircuito": "CIRC. CON RESIDENCIA",
      "CategoriaTitulo": "DOCENTE",
      "CargoInferior": "-"
    },
    {
      "orden": 30,
      "dni": "29XXXX05",
      "apellidos": "ANDRES",
      "nombres": "DAVID CESAR",
      "TipoCircuito": "CIRC. CON RESIDENCIA",
      "CategoriaTitulo": "DOCENTE",
      "CargoInferior": "-"
    },
    {
      "orden": 49,
      "dni": "39XXXX99",
      "apellidos": "RIOS ORDOÑEZ",
      "nombres": "JONATHAN NICOLAS",
      "TipoCircuito": "CIRC. CON RESIDENCIA",
      "CategoriaTitulo": "DOCENTE",
      "CargoInferior": "-"
    },
    {
      "orden": 53,
      "dni": "34XXXX04",
      "apellidos": "ABELLA",
      "nombres": "JULIO MAURICIO",
      "TipoCircuito": "CIRC. CON RESIDENCIA",
      "CategoriaTitulo": "DOCENTE",
      "CargoInferior": "-"
    },
    {
      "orden": 61,
      "dni": "30XXXX00",
      "apellidos": "BULACIO LOPEZ",
      "nombres": "MARCOS AUGUSTO",
      "TipoCircuito": "CIRC. CON RESIDENCIA",
      "CategoriaTitulo": "DOCENTE",
      "CargoInferior": "-"
    },
    {
      "orden": 67,
      "dni": "26XXXX76",
      "apellidos": "DIAZ",
      "nombres": "PAULA CAROLINA",
      "TipoCircuito": "CIRC. CON RESIDENCIA",
      "CategoriaTitulo": "DOCENTE",
      "CargoInferior": "-"
    },
    {
      "orden": 94,
      "dni": "23XXXX15",
      "apellidos": "LOBO",
      "nombres": "SANDRA DEL VALLE",
      "TipoCircuito": "CIRC. CON RESIDENCIA",
      "CategoriaTitulo": "DOCENTE",
      "CargoInferior": "-"
    },
    {
      "orden": 103,
      "dni": "28XXXX51",
      "apellidos": "ROLDAN",
      "nombres": "JULIA PAOLA",
      "TipoCircuito": "CIRC. CON RESIDENCIA",
      "CategoriaTitulo": "DOCENTE",
      "CargoInferior": "-"
    },
    {
      "orden": 105,
      "dni": "34XXXX43",
      "apellidos": "PEREZ",
      "nombres": "JOSE MANUEL",
      "TipoCircuito": "CIRC. CON RESIDENCIA",
      "CategoriaTitulo": "DOCENTE",
      "CargoInferior": "-"
    },
    {
      "orden": 112,
      "dni": "25XXXX33",
      "apellidos": "MONTEROS",
      "nombres": "ULISES DURVAL",
      "TipoCircuito": "CIRC. CON RESIDENCIA",
      "CategoriaTitulo": "DOCENTE",
      "CargoInferior": "-"
    },
    {
      "orden": 115,
      "dni": "39XXXX58",
      "apellidos": "CORTES",
      "nombres": "ANAHI LUCIANA",
      "TipoCircuito": "CIRC. CON RESIDENCIA",
      "CategoriaTitulo": "DOCENTE",
      "CargoInferior": "-"
    },
    {
      "orden": 116,
      "dni": "37XXXX52",
      "apellidos": "ROSALES CHÁVEZ",
      "nombres": "CLARA ANABELLA",
      "TipoCircuito": "CIRC. CON RESIDENCIA",
      "CategoriaTitulo": "DOCENTE",
      "CargoInferior": "-"
    },
    {
      "orden": 130,
      "dni": "34XXXX42",
      "apellidos": "ARCE",
      "nombres": "MANUEL EZEQUIEL",
      "TipoCircuito": "CIRC. CON RESIDENCIA",
      "CategoriaTitulo": "DOCENTE",
      "CargoInferior": "-"
    },
    {
      "orden": 150,
      "dni": "38XXXX84",
      "apellidos": "BARRERA",
      "nombres": "DAIANA TERESA",
      "TipoCircuito": "CIRC. CON RESIDENCIA",
      "CategoriaTitulo": "DOCENTE",
      "CargoInferior": "-"
    },
    {
      "orden": 167,
      "dni": "30XXXX05",
      "apellidos": "PUJOL",
      "nombres": "MARIA DE LAS MERCEDES",
      "TipoCircuito": "CIRC. CON RESIDENCIA",
      "CategoriaTitulo": "DOCENTE",
      "CargoInferior": "-"
    },
    {
      "orden": 168,
      "dni": "28XXXX00",
      "apellidos": "AGUIRRE",
      "nombres": "ÁNGEL ROQUE",
      "TipoCircuito": "CIRC. CON RESIDENCIA",
      "CategoriaTitulo": "DOCENTE",
      "CargoInferior": "-"
    },
    {
      "orden": 189,
      "dni": "18XXXX94",
      "apellidos": "GARAY",
      "nombres": "MARIA MERCEDES",
      "TipoCircuito": "CIRC. CON RESIDENCIA",
      "CategoriaTitulo": "DOCENTE",
      "CargoInferior": "-"
    },
    {
      "orden": 30,
      "dni": "28XXXX88",
      "apellidos": "VERA",
      "nombres": "RAMON ENRIQUE",
      "TipoCircuito": "CIRC. SIN RESIDENCIA",
      "CategoriaTitulo": "DOCENTE",
      "CargoInferior": "-"
    },
    {
      "orden": 59,
      "dni": "29XXXX32",
      "apellidos": "FARIAS",
      "nombres": "MARIA DE LOS ANGELES",
      "TipoCircuito": "CIRC. SIN RESIDENCIA",
      "CategoriaTitulo": "DOCENTE",
      "CargoInferior": "-"
    },
    {
      "orden": 71,
      "dni": "20XXXX12",
      "apellidos": "ZAMORA",
      "nombres": "ADRIANA DEL CARMEN",
      "TipoCircuito": "CIRC. SIN RESIDENCIA",
      "CategoriaTitulo": "DOCENTE",
      "CargoInferior": "-"
    },
    {
      "orden": 79,
      "dni": "28XXXX94",
      "apellidos": "ORELLANA",
      "nombres": "MAURICIO JOSE",
      "TipoCircuito": "CIRC. SIN RESIDENCIA",
      "CategoriaTitulo": "DOCENTE",
      "CargoInferior": "-"
    },
    {
      "orden": 105,
      "dni": "33XXXX10",
      "apellidos": "CUEVAS",
      "nombres": "KARINA MABEL",
      "TipoCircuito": "CIRC. SIN RESIDENCIA",
      "CategoriaTitulo": "DOCENTE",
      "CargoInferior": "-"
    },
    {
      "orden": 115,
      "dni": "31XXXX82",
      "apellidos": "ROLLATE DEL CORRO",
      "nombres": "GABRIELA PAOLA",
      "TipoCircuito": "CIRC. SIN RESIDENCIA",
      "CategoriaTitulo": "DOCENTE",
      "CargoInferior": "-"
    },
    {
      "orden": 121,
      "dni": "38XXXX20",
      "apellidos": "RUBINI ZAMORA",
      "nombres": "PAULA ADRIANA",
      "TipoCircuito": "CIRC. SIN RESIDENCIA",
      "CategoriaTitulo": "DOCENTE",
      "CargoInferior": "-"
    },
    {
      "orden": 154,
      "dni": "29XXXX48",
      "apellidos": "POSSE DE BOECK",
      "nombres": "SEBASTIAN ENRIQUE",
      "TipoCircuito": "CIRC. SIN RESIDENCIA",
      "CategoriaTitulo": "DOCENTE",
      "CargoInferior": "-"
    },
    {
      "orden": 159,
      "dni": "35XXXX69",
      "apellidos": "VILLA",
      "nombres": "MAITE SOLEDAD",
      "TipoCircuito": "CIRC. SIN RESIDENCIA",
      "CategoriaTitulo": "DOCENTE",
      "CargoInferior": "-"
    },
    {
      "orden": 160,
      "dni": "28XXXX24",
      "apellidos": "QUIROGA",
      "nombres": "ELIANA ANDREA DEL VALLE",
      "TipoCircuito": "CIRC. SIN RESIDENCIA",
      "CategoriaTitulo": "DOCENTE",
      "CargoInferior": "-"
    },
    {
      "orden": 162,
      "dni": "34XXXX97",
      "apellidos": "MARTINEZ",
      "nombres": "MARIA DE LOS ANGELES",
      "TipoCircuito": "CIRC. SIN RESIDENCIA",
      "CategoriaTitulo": "DOCENTE",
      "CargoInferior": "-"
    },
    {
      "orden": 182,
      "dni": "32XXXX30",
      "apellidos": "ROMERO",
      "nombres": "ROCIO",
      "TipoCircuito": "CIRC. SIN RESIDENCIA",
      "CategoriaTitulo": "DOCENTE",
      "CargoInferior": "-"
    },
    {
      "orden": 218,
      "dni": "24XXXX28",
      "apellidos": "FARACI",
      "nombres": "EDUARDO ADRIAN",
      "TipoCircuito": "CIRC. SIN RESIDENCIA",
      "CategoriaTitulo": "DOCENTE",
      "CargoInferior": "-"
    },
    {
      "orden": 276,
      "dni": "26XXXX97",
      "apellidos": "MORENO",
      "nombres": "GRACIELA SUSANA",
      "TipoCircuito": "CIRC. SIN RESIDENCIA",
      "CategoriaTitulo": "DOCENTE",
      "CargoInferior": "-"
    },
    {
      "orden": 281,
      "dni": "27XXXX96",
      "apellidos": "ROBLEDO",
      "nombres": "MARIA GABRIELA",
      "TipoCircuito": "CIRC. SIN RESIDENCIA",
      "CategoriaTitulo": "DOCENTE",
      "CargoInferior": "-"
    },
    {
      "orden": 323,
      "dni": "36XXXX38",
      "apellidos": "CARO ABRAHAM",
      "nombres": "MARIA JOSE",
      "TipoCircuito": "CIRC. SIN RESIDENCIA",
      "CategoriaTitulo": "DOCENTE",
      "CargoInferior": "-"
    },
    {
      "orden": 1,
      "dni": "31XXXX70",
      "apellidos": "LOPEZ PEÑA",
      "nombres": "JORGE RAMON",
      "TipoCircuito": "CIRC. SIN RESIDENCIA",
      "CategoriaTitulo": "HABILITANTE",
      "CargoInferior": "-"
    },
    {
      "orden": 14,
      "dni": "25XXXX47",
      "apellidos": "LAZARTE ACOSTA MONTE",
      "nombres": "CLAUDIA DE LOS ANGELES",
      "TipoCircuito": "CIRC. SIN RESIDENCIA",
      "CategoriaTitulo": "HABILITANTE",
      "CargoInferior": "-"
    },
    {
      "orden": 23,
      "dni": "38XXXX69",
      "apellidos": "MAS MAHMUD",
      "nombres": "CYNTHIA YASMIN",
      "TipoCircuito": "CIRC. SIN RESIDENCIA",
      "CategoriaTitulo": "HABILITANTE",
      "CargoInferior": "-"
    }
  ]
}
