{
  "metadata": {
    "vacante_id": 5610,
    "padron_id": 9515
  },
  "postulantes": [
    {
      "orden": 51,
      "dni": "20XXXX07",
      "apellidos": "ARIAS",
      "nombres": "MARIA ALEJANDRA",
      "TipoCircuito": "CON RESIDENCIA",
      "CategoriaTitulo": "DOCENTE",
      "CargoInferior": "-"
    },
    {
      "orden": 94,
      "dni": "20XXXX18",
      "apellidos": "BUSTOS                                  ",
      "nombres": "CLAUDIA MARCELA                         ",
      "TipoCircuito": "SIN RESIDENCIA",
      "CategoriaTitulo": "DOCENTE",
      "CargoInferior": "-"
    }
  ]
}
