{
  "metadata": {
    "vacante_id": 51954,
    "padron_id": 92803
  },
  "postulantes": [
    {
      "orden": 268,
      "dni": "33XXXX44",
      "apellidos": "ARIAS",
      "nombres": "MARIA LORENA",
      "TipoCircuito": "CON RESIDENCIA",
      "CategoriaTitulo": "DOCENTE",
      "CargoInferior": "-"
    },
    {
      "orden": 309,
      "dni": "26XXXX99",
      "apellidos": "RODRIGUEZ",
      "nombres": "SUSANA ELIZABETH",
      "TipoCircuito": "CON RESIDENCIA",
      "CategoriaTitulo": "DOCENTE",
      "CargoInferior": "-"
    },
    {
      "orden": 326,
      "dni": "38XXXX91",
      "apellidos": "CHAVEZ VILLAGRA",
      "nombres": "FLAVIA MICAELA",
      "TipoCircuito": "CON RESIDENCIA",
      "CategoriaTitulo": "DOCENTE",
      "CargoInferior": "-"
    },
    {
      "orden": 484,
      "dni": "30XXXX35",
      "apellidos": "GAMBOA LOPEZ",
      "nombres": "ESTELLA MARYS",
      "TipoCircuito": "CON RESIDENCIA",
      "CategoriaTitulo": "DOCENTE",
      "CargoInferior": "-"
    },
    {
      "orden": 495,
      "dni": "21XXXX94",
      "apellidos": "HERRERA",
      "nombres": "ANALIA LUISA DEL VALLE",
      "TipoCircuito": "CON RESIDENCIA",
      "CategoriaTitulo": "DOCENTE",
      "CargoInferior": "-"
    },
    {
      "orden": 497,
      "dni": "38XXXX30",
      "apellidos": "FLORES",
      "nombres": "RITA NOEMÍ",
      "TipoCircuito": "CON RESIDENCIA",
      "CategoriaTitulo": "DOCENTE",
      "CargoInferior": "-"
    },
    {
      "orden": 579,
      "dni": "36XXXX79",
      "apellidos": "ALE",
      "nombres": "MARIA BEATRIZ",
      "TipoCircuito": "CON RESIDENCIA",
      "CategoriaTitulo": "DOCENTE",
      "CargoInferior": "-"
    },
    {
      "orden": 586,
      "dni": "31XXXX33",
      "apellidos": "CHAILE",
      "nombres": "MARIELA ELIZABETH",
      "TipoCircuito": "CON RESIDENCIA",
      "CategoriaTitulo": "DOCENTE",
      "CargoInferior": "-"
    },
    {
      "orden": 587,
      "dni": "38XXXX75",
      "apellidos": "CRUZ",
      "nombres": "NOELIA ADRIANA",
      "TipoCircuito": "CON RESIDENCIA",
      "CategoriaTitulo": "DOCENTE",
      "CargoInferior": "-"
    },
    {
      "orden": 678,
      "dni": "40XXXX81",
      "apellidos": "CORDOBA",
      "nombres": "VICTORIA ANABELA",
      "TipoCircuito": "CON RESIDENCIA",
      "CategoriaTitulo": "DOCENTE",
      "CargoInferior": "-"
    },
    {
      "orden": 768,
      "dni": "39XXXX08",
      "apellidos": "MARRAS",
      "nombres": "FLAVIA GUADALUPE",
      "TipoCircuito": "CON RESIDENCIA",
      "CategoriaTitulo": "DOCENTE",
      "CargoInferior": "-"
    },
    {
      "orden": 770,
      "dni": "41XXXX70",
      "apellidos": "MIRANDA",
      "nombres": "MARÍA BELÉN",
      "TipoCircuito": "CON RESIDENCIA",
      "CategoriaTitulo": "DOCENTE",
      "CargoInferior": "-"
    },
    {
      "orden": 783,
      "dni": "37XXXX50",
      "apellidos": "PEDRAZA",
      "nombres": "NANCY GABRIELA",
      "TipoCircuito": "CON RESIDENCIA",
      "CategoriaTitulo": "DOCENTE",
      "CargoInferior": "-"
    },
    {
      "orden": 787,
      "dni": "33XXXX80",
      "apellidos": "AGUILAR",
      "nombres": "LUCIA VERONICA",
      "TipoCircuito": "CON RESIDENCIA",
      "CategoriaTitulo": "DOCENTE",
      "CargoInferior": "-"
    },
    {
      "orden": 748,
      "dni": "40XXXX78",
      "apellidos": "HERRERA",
      "nombres": "LORENA ELIZABETH",
      "TipoCircuito": "SIN RESIDENCIA",
      "CategoriaTitulo": "DOCENTE",
      "CargoInferior": "-"
    },
    {
      "orden": 833,
      "dni": "22XXXX99",
      "apellidos": "FIAD",
      "nombres": "MARIA CECILIA",
      "TipoCircuito": "SIN RESIDENCIA",
      "CategoriaTitulo": "DOCENTE",
      "CargoInferior": "-"
    },
    {
      "orden": 916,
      "dni": "23XXXX46",
      "apellidos": "HERRERA",
      "nombres": "MARIA LUJAN",
      "TipoCircuito": "SIN RESIDENCIA",
      "CategoriaTitulo": "DOCENTE",
      "CargoInferior": "-"
    }
  ]
}
