{
  "metadata": {
    "vacante_id": 81423,
    "padron_id": 143526
  },
  "postulantes": [
    {
      "orden": 593,
      "dni": "21XXXX61",
      "apellidos": "MERCADO",
      "nombres": "VIVIANA DEL CARMEN",
      "TipoCircuito": "CON RESIDENCIA",
      "CategoriaTitulo": "DOCENTE",
      "CargoInferior": "-"
    },
    {
      "orden": 624,
      "dni": "33XXXX98",
      "apellidos": "NORIEGA",
      "nombres": "ANA SOFIA",
      "TipoCircuito": "CON RESIDENCIA",
      "CategoriaTitulo": "DOCENTE",
      "CargoInferior": "-"
    },
    {
      "orden": 696,
      "dni": "35XXXX98",
      "apellidos": "VALLEJO",
      "nombres": "MARIA BELEN",
      "TipoCircuito": "CON RESIDENCIA",
      "CategoriaTitulo": "DOCENTE",
      "CargoInferior": "-"
    },
    {
      "orden": 923,
      "dni": "40XXXX11",
      "apellidos": "SOSA COSTILLA",
      "nombres": "CAMILA BELEN",
      "TipoCircuito": "CON RESIDENCIA",
      "CategoriaTitulo": "DOCENTE",
      "CargoInferior": "-"
    },
    {
      "orden": 794,
      "dni": "23XXXX44",
      "apellidos": "VILLALVA",
      "nombres": "ROSA MARIA",
      "TipoCircuito": "SIN RESIDENCIA",
      "CategoriaTitulo": "DOCENTE",
      "CargoInferior": "-"
    },
    {
      "orden": 983,
      "dni": "27XXXX10",
      "apellidos": "JUAREZ",
      "nombres": "MARTA SOLEDAD",
      "TipoCircuito": "SIN RESIDENCIA",
      "CategoriaTitulo": "DOCENTE",
      "CargoInferior": "-"
    },
    {
      "orden": 1173,
      "dni": "22XXXX67",
      "apellidos": "CORDOBA",
      "nombres": "MARIANA INES",
      "TipoCircuito": "SIN RESIDENCIA",
      "CategoriaTitulo": "DOCENTE",
      "CargoInferior": "-"
    },
    {
      "orden": 1234,
      "dni": "41XXXX51",
      "apellidos": "ANTELO",
      "nombres": "ANA GABRIELA",
      "TipoCircuito": "SIN RESIDENCIA",
      "CategoriaTitulo": "DOCENTE",
      "CargoInferior": "-"
    }
  ]
}
