{
  "vacantes": [
    {
      "id": 196951,
      "ocu_cargo_id": 3439681,
      "establecimiento": "[9000828/00] INST. DE ENSEÑANZA SUPERIOR TAFI VIEJO",
      "cargo": "HORAS CATEDRAS TERCIARIO - 902##",
      "nivel": "SUPERIOR",
      "modalidad": "COMÚN",
      "materia": "TALLER DE INTEG. Y ENS. DE LENG. ART, EXPRESION CORPORAL, MUSICA Y PLASTICA",
      "cargos_id": 102958,
      "organismo_id": 605
    },
    {
      "id": 196952,
      "ocu_cargo_id": 3439683,
      "establecimiento": "[9000828/00] INST. DE ENSEÑANZA SUPERIOR TAFI VIEJO",
      "cargo": "HORAS CATEDRAS TERCIARIO - 902##",
      "nivel": "SUPERIOR",
      "modalidad": "COMÚN",
      "materia": "TALLER DE INTEG. Y ENS. DE LENG. ART, EXPRESION CORPORAL, MUSICA Y PLASTICA",
      "cargos_id": 23252,
      "organismo_id": 605
    }
  ]
}
