{
  "metadata": {
    "vacante_id": 51568,
    "padron_id": 93754
  },
  "postulantes": [
    {
      "orden": 4,
      "dni": "28XXXX69",
      "apellidos": "VISCHI",
      "nombres": "NELSON ALFREDO",
      "TipoCircuito": "NINGUNO",
      "CategoriaTitulo": "DOCENTE",
      "CargoInferior": "-"
    },
    {
      "orden": 11,
      "dni": "27XXXX01",
      "apellidos": "RUIZ LEMA",
      "nombres": "JORGE AUGUSTO",
      "TipoCircuito": "NINGUNO",
      "CategoriaTitulo": "DOCENTE",
      "CargoInferior": "-"
    },
    {
      "orden": 17,
      "dni": "30XXXX05",
      "apellidos": "MOYA",
      "nombres": "CAROLA FERNANDA",
      "TipoCircuito": "NINGUNO",
      "CategoriaTitulo": "DOCENTE",
      "CargoInferior": "-"
    },
    {
      "orden": 23,
      "dni": "39XXXX04",
      "apellidos": "MEDINA",
      "nombres": "MARIA BELEN",
      "TipoCircuito": "NINGUNO",
      "CategoriaTitulo": "DOCENTE",
      "CargoInferior": "-"
    },
    {
      "orden": 46,
      "dni": "39XXXX15",
      "apellidos": "CUELLAR",
      "nombres": "EDGAR MAXIMILIANO",
      "TipoCircuito": "NINGUNO",
      "CategoriaTitulo": "DOCENTE",
      "CargoInferior": "-"
    },
    {
      "orden": 59,
      "dni": "37XXXX31",
      "apellidos": "JIMENEZ",
      "nombres": "CARLOS RAMON RODRIGO",
      "TipoCircuito": "NINGUNO",
      "CategoriaTitulo": "DOCENTE",
      "CargoInferior": "-"
    },
    {
      "orden": 66,
      "dni": "27XXXX28",
      "apellidos": "RIVADENEIRA",
      "nombres": "ANGELICA LORENA",
      "TipoCircuito": "NINGUNO",
      "CategoriaTitulo": "DOCENTE",
      "CargoInferior": "-"
    }
  ]
}
