{
  "metadata": {
    "vacante_id": 53743,
    "padron_id": 95750
  },
  "postulantes": [
    {
      "orden": 28,
      "dni": "27XXXX36",
      "apellidos": "TEJERINA",
      "nombres": "MIRIAM EDITH",
      "TipoCircuito": "CIRC. CON RESIDENCIA",
      "CategoriaTitulo": "DOCENTE",
      "CargoInferior": "-"
    },
    {
      "orden": 29,
      "dni": "36XXXX88",
      "apellidos": "MOLINA",
      "nombres": "IVANA BELEN",
      "TipoCircuito": "CIRC. CON RESIDENCIA",
      "CategoriaTitulo": "DOCENTE",
      "CargoInferior": "-"
    },
    {
      "orden": 35,
      "dni": "26XXXX07",
      "apellidos": "LUCENA",
      "nombres": "MARÍA CECILIA",
      "TipoCircuito": "CIRC. CON RESIDENCIA",
      "CategoriaTitulo": "DOCENTE",
      "CargoInferior": "-"
    },
    {
      "orden": 52,
      "dni": "31XXXX16",
      "apellidos": "JUAREZ",
      "nombres": "JUAN MANUEL",
      "TipoCircuito": "CIRC. CON RESIDENCIA",
      "CategoriaTitulo": "DOCENTE",
      "CargoInferior": "-"
    },
    {
      "orden": 55,
      "dni": "24XXXX67",
      "apellidos": "RODRIGUEZ",
      "nombres": "GRACIELA DOLORES",
      "TipoCircuito": "CIRC. CON RESIDENCIA",
      "CategoriaTitulo": "DOCENTE",
      "CargoInferior": "-"
    },
    {
      "orden": 58,
      "dni": "33XXXX83",
      "apellidos": "REYES",
      "nombres": "LOURDES JIMENA",
      "TipoCircuito": "CIRC. CON RESIDENCIA",
      "CategoriaTitulo": "DOCENTE",
      "CargoInferior": "-"
    },
    {
      "orden": 65,
      "dni": "31XXXX24",
      "apellidos": "VERA JALUF",
      "nombres": "LAURA ANDREA",
      "TipoCircuito": "CIRC. CON RESIDENCIA",
      "CategoriaTitulo": "DOCENTE",
      "CargoInferior": "-"
    },
    {
      "orden": 68,
      "dni": "39XXXX56",
      "apellidos": "GARCIA",
      "nombres": "PRISCILA ESTEFANIA",
      "TipoCircuito": "CIRC. CON RESIDENCIA",
      "CategoriaTitulo": "DOCENTE",
      "CargoInferior": "-"
    },
    {
      "orden": 74,
      "dni": "32XXXX23",
      "apellidos": "LOPEZ",
      "nombres": "SILVINA NOELIA",
      "TipoCircuito": "CIRC. CON RESIDENCIA",
      "CategoriaTitulo": "DOCENTE",
      "CargoInferior": "-"
    },
    {
      "orden": 89,
      "dni": "26XXXX29",
      "apellidos": "ROSALES",
      "nombres": "PAOLA GUADALUPE",
      "TipoCircuito": "CIRC. CON RESIDENCIA",
      "CategoriaTitulo": "DOCENTE",
      "CargoInferior": "-"
    },
    {
      "orden": 90,
      "dni": "40XXXX12",
      "apellidos": "TORRES",
      "nombres": "CAMILA MARIEL",
      "TipoCircuito": "CIRC. CON RESIDENCIA",
      "CategoriaTitulo": "DOCENTE",
      "CargoInferior": "-"
    },
    {
      "orden": 98,
      "dni": "29XXXX05",
      "apellidos": "GONZALEZ",
      "nombres": "CAROLINA MARISA",
      "TipoCircuito": "CIRC. CON RESIDENCIA",
      "CategoriaTitulo": "DOCENTE",
      "CargoInferior": "-"
    },
    {
      "orden": 100,
      "dni": "30XXXX76",
      "apellidos": "SANCHEZ",
      "nombres": "ALEJANDRA NOEMI",
      "TipoCircuito": "CIRC. CON RESIDENCIA",
      "CategoriaTitulo": "DOCENTE",
      "CargoInferior": "-"
    },
    {
      "orden": 107,
      "dni": "35XXXX60",
      "apellidos": "DIAZ BARROS",
      "nombres": "SARA LIA",
      "TipoCircuito": "CIRC. CON RESIDENCIA",
      "CategoriaTitulo": "DOCENTE",
      "CargoInferior": "-"
    },
    {
      "orden": 113,
      "dni": "39XXXX45",
      "apellidos": "JUAREZ",
      "nombres": "MICAELA",
      "TipoCircuito": "CIRC. CON RESIDENCIA",
      "CategoriaTitulo": "DOCENTE",
      "CargoInferior": "-"
    },
    {
      "orden": 114,
      "dni": "28XXXX22",
      "apellidos": "GIMENEZ",
      "nombres": "IVANA DE LAS MERCEDES",
      "TipoCircuito": "CIRC. CON RESIDENCIA",
      "CategoriaTitulo": "DOCENTE",
      "CargoInferior": "-"
    },
    {
      "orden": 132,
      "dni": "37XXXX03",
      "apellidos": "VARELA",
      "nombres": "CYNTHIA ANTONELLA",
      "TipoCircuito": "CIRC. CON RESIDENCIA",
      "CategoriaTitulo": "DOCENTE",
      "CargoInferior": "-"
    },
    {
      "orden": 136,
      "dni": "18XXXX66",
      "apellidos": "BOLLOLI",
      "nombres": "MARIA MERCEDES",
      "TipoCircuito": "CIRC. CON RESIDENCIA",
      "CategoriaTitulo": "DOCENTE",
      "CargoInferior": "-"
    },
    {
      "orden": 140,
      "dni": "40XXXX88",
      "apellidos": "MOLINA",
      "nombres": "FLORENCIA AGUSTINA",
      "TipoCircuito": "CIRC. CON RESIDENCIA",
      "CategoriaTitulo": "DOCENTE",
      "CargoInferior": "-"
    },
    {
      "orden": 142,
      "dni": "31XXXX53",
      "apellidos": "TAWIL                                   ",
      "nombres": "STELLA MARYS                            ",
      "TipoCircuito": "CIRC. CON RESIDENCIA",
      "CategoriaTitulo": "DOCENTE",
      "CargoInferior": "-"
    },
    {
      "orden": 143,
      "dni": "26XXXX61",
      "apellidos": "FERREYRA",
      "nombres": "ANALIA GRACIELA",
      "TipoCircuito": "CIRC. CON RESIDENCIA",
      "CategoriaTitulo": "DOCENTE",
      "CargoInferior": "-"
    },
    {
      "orden": 146,
      "dni": "20XXXX84",
      "apellidos": "GARCIA",
      "nombres": "ADRIANA ESTER",
      "TipoCircuito": "CIRC. CON RESIDENCIA",
      "CategoriaTitulo": "DOCENTE",
      "CargoInferior": "-"
    },
    {
      "orden": 152,
      "dni": "38XXXX26",
      "apellidos": "CASTELLI",
      "nombres": "TANIA TAMARA",
      "TipoCircuito": "CIRC. CON RESIDENCIA",
      "CategoriaTitulo": "DOCENTE",
      "CargoInferior": "-"
    },
    {
      "orden": 156,
      "dni": "30XXXX34",
      "apellidos": "SIR ALBORNOZ",
      "nombres": "ELIANA DEL VALLE",
      "TipoCircuito": "CIRC. CON RESIDENCIA",
      "CategoriaTitulo": "DOCENTE",
      "CargoInferior": "-"
    },
    {
      "orden": 177,
      "dni": "27XXXX63",
      "apellidos": "ACOSTA",
      "nombres": "NADIA SOLEDAD",
      "TipoCircuito": "CIRC. CON RESIDENCIA",
      "CategoriaTitulo": "DOCENTE",
      "CargoInferior": "-"
    },
    {
      "orden": 186,
      "dni": "34XXXX70",
      "apellidos": "ROJAS",
      "nombres": "JOSÉ HERNÁN",
      "TipoCircuito": "CIRC. CON RESIDENCIA",
      "CategoriaTitulo": "DOCENTE",
      "CargoInferior": "-"
    },
    {
      "orden": 199,
      "dni": "35XXXX16",
      "apellidos": "MONASTERIO ",
      "nombres": "ROSA FATIMA",
      "TipoCircuito": "CIRC. CON RESIDENCIA",
      "CategoriaTitulo": "DOCENTE",
      "CargoInferior": "-"
    },
    {
      "orden": 201,
      "dni": "20XXXX86",
      "apellidos": "LIZARRAGA REGUERA",
      "nombres": "NORA PATRICIA",
      "TipoCircuito": "CIRC. CON RESIDENCIA",
      "CategoriaTitulo": "DOCENTE",
      "CargoInferior": "-"
    },
    {
      "orden": 28,
      "dni": "35XXXX61",
      "apellidos": "RACEDO",
      "nombres": "DARIO SEBASTIAN",
      "TipoCircuito": "CIRC. SIN RESIDENCIA",
      "CategoriaTitulo": "DOCENTE",
      "CargoInferior": "-"
    },
    {
      "orden": 45,
      "dni": "33XXXX70",
      "apellidos": "BRAVO",
      "nombres": "ALICIA INÉS",
      "TipoCircuito": "CIRC. SIN RESIDENCIA",
      "CategoriaTitulo": "DOCENTE",
      "CargoInferior": "-"
    },
    {
      "orden": 67,
      "dni": "32XXXX14",
      "apellidos": "SANTILLAN",
      "nombres": "ADRIANA ISABEL",
      "TipoCircuito": "CIRC. SIN RESIDENCIA",
      "CategoriaTitulo": "DOCENTE",
      "CargoInferior": "-"
    },
    {
      "orden": 68,
      "dni": "23XXXX81",
      "apellidos": "LOPEZ NINOFF",
      "nombres": "GUILLERMO NICOLAS",
      "TipoCircuito": "CIRC. SIN RESIDENCIA",
      "CategoriaTitulo": "DOCENTE",
      "CargoInferior": "-"
    },
    {
      "orden": 141,
      "dni": "37XXXX17",
      "apellidos": "PASCUAL",
      "nombres": "JULIETA CONSTANZA",
      "TipoCircuito": "CIRC. SIN RESIDENCIA",
      "CategoriaTitulo": "DOCENTE",
      "CargoInferior": "-"
    },
    {
      "orden": 142,
      "dni": "37XXXX18",
      "apellidos": "ROCHA",
      "nombres": "ROXANA ANABEL",
      "TipoCircuito": "CIRC. SIN RESIDENCIA",
      "CategoriaTitulo": "DOCENTE",
      "CargoInferior": "-"
    },
    {
      "orden": 150,
      "dni": "39XXXX40",
      "apellidos": "ZANCARINI",
      "nombres": "NOELIA JANINA",
      "TipoCircuito": "CIRC. SIN RESIDENCIA",
      "CategoriaTitulo": "DOCENTE",
      "CargoInferior": "-"
    },
    {
      "orden": 159,
      "dni": "37XXXX76",
      "apellidos": "VAQUERO",
      "nombres": "MARIA SOFIA",
      "TipoCircuito": "CIRC. SIN RESIDENCIA",
      "CategoriaTitulo": "DOCENTE",
      "CargoInferior": "-"
    },
    {
      "orden": 196,
      "dni": "34XXXX08",
      "apellidos": "ALVAREZ",
      "nombres": "FLORENCIA SOLEDAD",
      "TipoCircuito": "CIRC. SIN RESIDENCIA",
      "CategoriaTitulo": "DOCENTE",
      "CargoInferior": "-"
    },
    {
      "orden": 200,
      "dni": "38XXXX52",
      "apellidos": "DIAZ",
      "nombres": "FRANCISCO EMMANUEL",
      "TipoCircuito": "CIRC. SIN RESIDENCIA",
      "CategoriaTitulo": "DOCENTE",
      "CargoInferior": "-"
    },
    {
      "orden": 244,
      "dni": "40XXXX85",
      "apellidos": "LEDESMA",
      "nombres": "PAMELA NAOMI",
      "TipoCircuito": "CIRC. SIN RESIDENCIA",
      "CategoriaTitulo": "DOCENTE",
      "CargoInferior": "-"
    },
    {
      "orden": 258,
      "dni": "32XXXX07",
      "apellidos": "VALENCIA DUGACHES",
      "nombres": "DAVID RICARDO",
      "TipoCircuito": "CIRC. SIN RESIDENCIA",
      "CategoriaTitulo": "DOCENTE",
      "CargoInferior": "-"
    },
    {
      "orden": 265,
      "dni": "30XXXX30",
      "apellidos": "CASTILLO",
      "nombres": "SILVINA LUCIANA",
      "TipoCircuito": "CIRC. SIN RESIDENCIA",
      "CategoriaTitulo": "DOCENTE",
      "CargoInferior": "-"
    },
    {
      "orden": 281,
      "dni": "32XXXX92",
      "apellidos": "PAEZ VALDEZ",
      "nombres": "ROMINA ELIZABETH",
      "TipoCircuito": "CIRC. SIN RESIDENCIA",
      "CategoriaTitulo": "DOCENTE",
      "CargoInferior": "-"
    },
    {
      "orden": 298,
      "dni": "38XXXX41",
      "apellidos": "AGUERA",
      "nombres": "ROXANA BEATRIZ",
      "TipoCircuito": "CIRC. SIN RESIDENCIA",
      "CategoriaTitulo": "DOCENTE",
      "CargoInferior": "-"
    },
    {
      "orden": 304,
      "dni": "34XXXX33",
      "apellidos": "GOMEZ",
      "nombres": "ROMINA VANESA",
      "TipoCircuito": "CIRC. SIN RESIDENCIA",
      "CategoriaTitulo": "DOCENTE",
      "CargoInferior": "-"
    },
    {
      "orden": 309,
      "dni": "37XXXX69",
      "apellidos": "VALDEZ",
      "nombres": "GISELLE STEFANIA",
      "TipoCircuito": "CIRC. SIN RESIDENCIA",
      "CategoriaTitulo": "DOCENTE",
      "CargoInferior": "-"
    },
    {
      "orden": 325,
      "dni": "29XXXX24",
      "apellidos": "RACEDO",
      "nombres": "SANDRA CARINA",
      "TipoCircuito": "CIRC. SIN RESIDENCIA",
      "CategoriaTitulo": "DOCENTE",
      "CargoInferior": "-"
    },
    {
      "orden": 390,
      "dni": "27XXXX81",
      "apellidos": "GOMEZ PARICCE",
      "nombres": "ALEJANDRA FATIMA",
      "TipoCircuito": "CIRC. SIN RESIDENCIA",
      "CategoriaTitulo": "DOCENTE",
      "CargoInferior": "-"
    },
    {
      "orden": 396,
      "dni": "25XXXX14",
      "apellidos": "ROYANO",
      "nombres": "MARIA LAURA DEL VALLE",
      "TipoCircuito": "CIRC. SIN RESIDENCIA",
      "CategoriaTitulo": "DOCENTE",
      "CargoInferior": "-"
    },
    {
      "orden": 399,
      "dni": "34XXXX30",
      "apellidos": "PÉREZ",
      "nombres": "MÓNICA VIVIANA",
      "TipoCircuito": "CIRC. SIN RESIDENCIA",
      "CategoriaTitulo": "DOCENTE",
      "CargoInferior": "-"
    }
  ]
}
