{
  "metadata": {
    "vacante_id": 23779,
    "padron_id": 43641
  },
  "postulantes": [
    {
      "orden": 5,
      "dni": "12XXXX67",
      "apellidos": "MARQUEZ SANCHEZ",
      "nombres": "JUAN CARLOS HUMBERTO",
      "TipoCircuito": "NINGUNO",
      "CategoriaTitulo": "DOCENTE",
      "CargoInferior": "-"
    },
    {
      "orden": 1,
      "dni": "38XXXX76",
      "apellidos": "BELMONTE",
      "nombres": "JAVIER NICOLAS",
      "TipoCircuito": "NINGUNO",
      "CategoriaTitulo": "SUPLETORIO",
      "CargoInferior": "-"
    },
    {
      "orden": 2,
      "dni": "37XXXX47",
      "apellidos": "RODRIGUEZ",
      "nombres": "EXEQUIEL ORLANDO",
      "TipoCircuito": "NINGUNO",
      "CategoriaTitulo": "SUPLETORIO",
      "CargoInferior": "-"
    },
    {
      "orden": 8,
      "dni": "36XXXX50",
      "apellidos": "URUEÑA",
      "nombres": "ANTONIO LINO",
      "TipoCircuito": "NINGUNO",
      "CategoriaTitulo": "SUPLETORIO",
      "CargoInferior": "-"
    },
    {
      "orden": 16,
      "dni": "16XXXX67",
      "apellidos": "SOSA",
      "nombres": "MARCOS RUBÉN",
      "TipoCircuito": "NINGUNO",
      "CategoriaTitulo": "SUPLETORIO",
      "CargoInferior": "-"
    },
    {
      "orden": 21,
      "dni": "37XXXX23",
      "apellidos": "VILLA",
      "nombres": "NELSON NICOLÁS",
      "TipoCircuito": "NINGUNO",
      "CategoriaTitulo": "SUPLETORIO",
      "CargoInferior": "-"
    },
    {
      "orden": 37,
      "dni": "40XXXX93",
      "apellidos": "CORREA",
      "nombres": "ESTEBAN FABIAN",
      "TipoCircuito": "NINGUNO",
      "CategoriaTitulo": "SUPLETORIO",
      "CargoInferior": "-"
    },
    {
      "orden": 43,
      "dni": "31XXXX23",
      "apellidos": "VERA RODRÍGUEZ",
      "nombres": "JOSÉ MANUEL",
      "TipoCircuito": "NINGUNO",
      "CategoriaTitulo": "SUPLETORIO",
      "CargoInferior": "-"
    }
  ]
}
